AUTHORS
CHANGES
LICENSE
MANIFEST.in
README.md
setup.py
cmsplugin_embedded_pages.egg-info/PKG-INFO
cmsplugin_embedded_pages.egg-info/SOURCES.txt
cmsplugin_embedded_pages.egg-info/dependency_links.txt
cmsplugin_embedded_pages.egg-info/requires.txt
cmsplugin_embedded_pages.egg-info/top_level.txt
cmsplugin_embeddedpages/__init__.py
cmsplugin_embeddedpages/cms_plugins.py
cmsplugin_embeddedpages/forms.py
cmsplugin_embeddedpages/models.py
cmsplugin_embeddedpages/lib/__init__.py
cmsplugin_embeddedpages/lib/choices.py
cmsplugin_embeddedpages/lib/formatting.py
cmsplugin_embeddedpages/migrations/0001_initial.py
cmsplugin_embeddedpages/migrations/0002_auto__add_field_pagepluginsettings_placeholders.py
cmsplugin_embeddedpages/migrations/0003_auto__del_field_pagepluginsettings_placeholders.py
cmsplugin_embeddedpages/migrations/0004_auto__add_field_pagepluginsettings_depth.py
cmsplugin_embeddedpages/migrations/0005_auto__del_field_pagepluginsettings_template__add_field_pagepluginsetti.py
cmsplugin_embeddedpages/migrations/__init__.py
cmsplugin_embeddedpages/templates/cmsplugin_embeddedpages/base.html
cmsplugin_embeddedpages/templates/cmsplugin_embeddedpages/layouts/groups/default.html
cmsplugin_embeddedpages/templates/cmsplugin_embeddedpages/layouts/pages/default.html