Metadata-Version: 1.0
Name: cmsplugin-embedded-pages
Version: 0.0.4
Summary: DjangoCMS plugin that allows for embedding other pages in placeholders
Home-page: http://github.com/airtonix/cmsplugin-embedded-pages
Author: Zenobius Jiricek
Author-email: airtonix@gmail.com
License: BSD
Keywords: django-cms,plugin,pages
Platform: UNKNOWN
Classifier: Development Status :: 4 - Beta
Classifier: Framework :: Django
Classifier: Intended Audience :: Developers
Classifier: License :: OSI Approved :: BSD License
Classifier: Operating System :: OS Independent
Classifier: Programming Language :: Python
Classifier: Topic :: Internet :: WWW/HTTP
